faceanalysis/__init__.py
faceanalysis/face_analysis.py
faceanalysis/models/__init__.py
faceanalysis/models/arcface_onnx.py
faceanalysis/models/attribute.py
faceanalysis/models/landmark.py
faceanalysis/models/retinaface.py
faceanalysis/utils/__init__.py
faceanalysis/utils/common.py
faceanalysis/utils/face_align.py
faceanalysis/utils/transform.py
face_analysis_lite-0.1.0.dist-info/LICENSE
face_analysis_lite-0.1.0.dist-info/METADATA
face_analysis_lite-0.1.0.dist-info/WHEEL
face_analysis_lite-0.1.0.dist-info/top_level.txt
face_analysis_lite-0.1.0.dist-info/RECORD
