Metadata-Version: 2.1
Name: face_analysis_lite
Version: 0.1.0
Summary: Library for facial region detection and extraction
Home-page: https://github.com/leonelhs/faceanalysis
Author: leonel hernandez
Author-email: leonelhs@gmail.com
Classifier: Programming Language :: Python :: 3
Classifier: License :: OSI Approved :: MIT License
Classifier: Operating System :: OS Independent
Requires-Python: >=3.6
License-File: LICENSE
Requires-Dist: onnx>=1.19.0
Requires-Dist: onnxruntime>=1.22.1
Requires-Dist: opencv-python>=4.12.0.88
Requires-Dist: scikit-image>=0.25.2
Requires-Dist: huggingface-hub>=0.35.3
